{
  "slug": "052-why-is-beauty-a-bah-concern",
  "depth": 70,
  "clarity": 75,
  "stereotype_avoidance": 65,
  "word_definition_questioning": 60,
  "assumption_questioning": 55,
  "teaching_clarity": 70,
  "evidence_quality": 50,
  "conversational_naturalness": 65,
  "believer_voice": 80,
  "archive_worthy": 60,
  "overall": 65,
  "strengths": [
    "Believer_voice is strong and consistent.",
    "Clarity in explaining Bahá'í principles.",
    "Depth in exploring beauty and detachment."
  ],
  "weaknesses": [
    "Lacks specific textual references.",
    "Limited questioning of assumptions.",
    "Misses deeper exploration of word meanings."
  ],
  "prompt_signal": "Incorporate more specific textual references and question assumptions more deeply.",
  "elapsedSec": "101.0"
}